spin2win/__init__.py
spin2win/__main__.py
spin2win/arena.py
spin2win/character.py
spin2win/game.py
spin2win/menu.py
spin2win/music.py
spin2win/text.py
spin2win/images/bird0.png
spin2win/sounds/battle_theme.mp3
spin2win/sounds/collision_defense.wav
spin2win/sounds/collision_small.wav
spin2win/sounds/dash.wav
spin2win/sounds/defense.wav
spin2win/sounds/destruction.wav
spin2win-0.2.1.dist-info/DESCRIPTION.rst
spin2win-0.2.1.dist-info/METADATA
spin2win-0.2.1.dist-info/RECORD
spin2win-0.2.1.dist-info/WHEEL
spin2win-0.2.1.dist-info/entry_points.txt
spin2win-0.2.1.dist-info/metadata.json
spin2win-0.2.1.dist-info/top_level.txt
