Metadata-Version: 2.0
Name: spin2win
Version: 0.2.1
Summary: SPIN2WIN!!!
Home-page: https://github.com/FilippeLeal/spin2win
Author: Karine Santos Valença
Author-email: valenca.karine@gmail.com
License: UNKNOWN
Platform: any
Classifier: Development Status :: 3 - Alpha
Classifier: License :: OSI Approved :: GNU General Public License (GPL)
Classifier: Operating System :: OS Independent
Classifier: Programming Language :: Python
Classifier: Programming Language :: Python :: 3
Classifier: Programming Language :: Python :: 3.3
Classifier: Programming Language :: Python :: 3.4
Classifier: Programming Language :: Python :: 3.5
Requires-Dist: FGAme
Requires-Dist: pygame
Provides-Extra: dev
Requires-Dist: python-boilerplate[dev]; extra == 'dev'
